ai_documentation_writer/__init__.py
ai_documentation_writer/__main__.py
ai_documentation_writer/flow_options.py
ai_documentation_writer/py.typed
ai_documentation_writer/documents/__init__.py
ai_documentation_writer/documents/flow/__init__.py
ai_documentation_writer/documents/flow/codebase_documentation.py
ai_documentation_writer/documents/flow/final_documentation.py
ai_documentation_writer/documents/flow/project_files.py
ai_documentation_writer/documents/flow/project_initial_description.py
ai_documentation_writer/documents/flow/user_input.py
ai_documentation_writer/flows/__init__.py
ai_documentation_writer/flows/step_01_prepare_project_files.py
ai_documentation_writer/flows/step_02_generate_initial_description.py
ai_documentation_writer/flows/step_03_document_codebase.py
ai_documentation_writer/flows/step_04_create_final_documentation.py
ai_documentation_writer/prompts/__init__.py
ai_documentation_writer/tasks/__init__.py
ai_documentation_writer/tasks/create_final_documentation/__init__.py
ai_documentation_writer/tasks/create_final_documentation/create_final_documentation.py
ai_documentation_writer/tasks/document_codebase/__init__.py
ai_documentation_writer/tasks/document_codebase/document_codebase.py
ai_documentation_writer/tasks/document_codebase/document_codebase_directory.py
ai_documentation_writer/tasks/filter_project_files/__init__.py
ai_documentation_writer/tasks/filter_project_files/filter_project_files.py
ai_documentation_writer/tasks/filter_project_files/models.py
ai_documentation_writer/tasks/generate_initial_description/__init__.py
ai_documentation_writer/tasks/generate_initial_description/generate_initial_description.py
ai_documentation_writer/tasks/generate_initial_description/models.py
ai_documentation_writer/tasks/prepare_project_files/__init__.py
ai_documentation_writer/tasks/prepare_project_files/clone_repository.py
ai_documentation_writer/tasks/prepare_project_files/select_files.py
ai_documentation_writer-0.1.1.dist-info/METADATA
ai_documentation_writer-0.1.1.dist-info/WHEEL
ai_documentation_writer-0.1.1.dist-info/entry_points.txt
ai_documentation_writer-0.1.1.dist-info/licenses/LICENSE
ai_documentation_writer-0.1.1.dist-info/RECORD
