Metadata-Version: 2.4
Name: ai-documentation-writer
Version: 0.1.1
Summary: AI-powered tool to automatically generate documentation for developers and AI Agents
Project-URL: Homepage, https://github.com/bbarwik/ai-documentation-writer
Project-URL: Repository, https://github.com/bbarwik/ai-documentation-writer
Project-URL: Issues, https://github.com/bbarwik/ai-documentation-writer/issues
Author-email: bbarwik <bbarwik@gmail.com>
License: MIT
License-File: LICENSE
Classifier: Development Status :: 4 - Beta
Classifier: Intended Audience :: Developers
Classifier: License :: OSI Approved :: MIT License
Classifier: Programming Language :: Python :: 3
Classifier: Programming Language :: Python :: 3.12
Classifier: Programming Language :: Python :: 3.13
Classifier: Topic :: Scientific/Engineering :: Artificial Intelligence
Classifier: Topic :: Software Development :: Libraries :: Python Modules
Classifier: Typing :: Typed
Requires-Python: >=3.12
Requires-Dist: ai-pipeline-core>=0.1.8
Requires-Dist: pydantic>=2.11.7
Provides-Extra: dev
Requires-Dist: basedpyright>=1.31.2; extra == 'dev'
Requires-Dist: bump2version>=1.0.1; extra == 'dev'
Requires-Dist: pre-commit>=4.3.0; extra == 'dev'
Requires-Dist: pytest-asyncio>=1.1.0; extra == 'dev'
Requires-Dist: pytest-cov>=5.0.0; extra == 'dev'
Requires-Dist: pytest-mock>=3.14.0; extra == 'dev'
Requires-Dist: pytest-xdist>=3.8.0; extra == 'dev'
Requires-Dist: pytest>=8.4.1; extra == 'dev'
Requires-Dist: ruff>=0.12.9; extra == 'dev'
